lingx/__init__.py
lingx/core/__init__.py
lingx/core/lang_features.py
lingx/core/lang_model.py
lingx/metrics/__init__.py
lingx/metrics/bilingual/__init__.py
lingx/metrics/bilingual/bcr.py
lingx/metrics/monolingual/__init__.py
lingx/metrics/monolingual/le.py
lingx/metrics/monolingual/nnd.py
lingx/metrics/psycholingual/__init__.py
lingx/metrics/psycholingual/dlt.py
lingx/metrics/psycholingual/idt.py
lingx/metrics/psycholingual/idt_dlt.py
lingx/utils/__init__.py
lingx/utils/download_lang_models.py
lingx/utils/lx.py
lingx/utils/plot.py
lingx/utils/critt/__init__.py
lingx/utils/critt/aligner.py
lingx/utils/critt/tables.py
tests/__init__.py
tests/test_bcr.py
tests/test_classic_examples.py
tests/test_dlt.py
tests/test_idt.py
tests/test_idt_dlt.py
tests/test_le.py
tests/test_nnd.py
lingx-0.1.6.dist-info/LICENSE
lingx-0.1.6.dist-info/METADATA
lingx-0.1.6.dist-info/WHEEL
lingx-0.1.6.dist-info/top_level.txt
lingx-0.1.6.dist-info/RECORD
