Metadata-Version: 2.1
Name: lingx
Version: 0.1.6
Summary: A library for introducing state-of-the-art metrics on measuring linguistic complexity
Home-page: https://github/ContentSide/lingx
Author: Mehdi Mirzapour
Author-email: mehdi.mirzapour@gmail.com
License: MIT
Platform: UNKNOWN
Requires-Python: >=3.6
License-File: LICENSE
Requires-Dist: stanza (==1.2.1)
Requires-Dist: numpy
Requires-Dist: pandas
Requires-Dist: treelib
Requires-Dist: matplotlib
